async_generator-stubs/__init__.pyi
outcome-stubs/__init__.pyi
trio-stubs/__init__.pyi
trio-stubs/abc.pyi
trio-stubs/from_thread.pyi
trio-stubs/lowlevel.pyi
trio-stubs/socket.pyi
trio-stubs/testing.pyi
trio-stubs/to_thread.pyi
trio_typing/__init__.py
trio_typing/__init__.pyi
trio_typing/_version.py
trio_typing/plugin.py
trio_typing/py.typed
trio_typing/_tests/__init__.py
trio_typing/_tests/datadriven.py
trio_typing/_tests/test_runtime.py
trio_typing/_tests/test_typecheck.py
trio_typing/_tests/test-data/async_generator.test
trio_typing/_tests/test-data/open-mode.test
trio_typing/_tests/test-data/outcome.test
trio_typing/_tests/test-data/taskstatus.test
trio_typing/_tests/test-data/trio-basic.test
trio_typing-0.9.0.dist-info/LICENSE
trio_typing-0.9.0.dist-info/LICENSE.APACHE2
trio_typing-0.9.0.dist-info/LICENSE.MIT
trio_typing-0.9.0.dist-info/METADATA
trio_typing-0.9.0.dist-info/WHEEL
trio_typing-0.9.0.dist-info/top_level.txt
trio_typing-0.9.0.dist-info/RECORD
