Metadata-Version: 2.1
Name: trio-typing
Version: 0.9.0
Summary: Static type checking support for Trio and related projects
Home-page: https://github.com/python-trio/trio-typing
Author: Joshua Oreman
Author-email: oremanj@gmail.com
License: MIT -or- Apache License 2.0
Keywords: async,trio,mypy
Classifier: License :: OSI Approved :: MIT License
Classifier: License :: OSI Approved :: Apache Software License
Classifier: Framework :: Trio
Classifier: Operating System :: POSIX :: Linux
Classifier: Operating System :: MacOS :: MacOS X
Classifier: Operating System :: POSIX :: BSD
Classifier: Operating System :: Microsoft :: Windows
Classifier: Programming Language :: Python :: 3 :: Only
Classifier: Programming Language :: Python :: 3.5
Classifier: Programming Language :: Python :: 3.6
Classifier: Programming Language :: Python :: Implementation :: CPython
Classifier: Programming Language :: Python :: Implementation :: PyPy
Classifier: Development Status :: 3 - Alpha
Classifier: Intended Audience :: Developers
License-File: LICENSE
License-File: LICENSE.APACHE2
License-File: LICENSE.MIT
Requires-Dist: trio (>=0.16.0)
Requires-Dist: typing-extensions (>=3.7.4)
Requires-Dist: mypy-extensions (>=0.4.2)
Requires-Dist: async-generator
Requires-Dist: packaging
Requires-Dist: importlib-metadata
Provides-Extra: mypy
Requires-Dist: mypy (>=0.920) ; extra == 'mypy'
